README.rst
setup.py
hp3parclient/__init__.py
hp3parclient/client.py
hp3parclient/exceptions.py
hp3parclient/file_client.py
hp3parclient/http.py
hp3parclient/ssh.py
hp3parclient/tcl_parser.py
hp3parclient.egg-info/PKG-INFO
hp3parclient.egg-info/SOURCES.txt
hp3parclient.egg-info/dependency_links.txt
hp3parclient.egg-info/requires.txt
hp3parclient.egg-info/top_level.txt
test/HP3ParClient_base.py
test/HP3ParMockServer_flask.py
test/HP3ParMockServer_ssh.py
test/__init__.py
test/test_HP3ParClient_CPG.py
test/test_HP3ParClient_Exception.py
test/test_HP3ParClient_FilePersona.py
test/test_HP3ParClient_FilePersona_Mock.py
test/test_HP3ParClient_HostSet.py
test/test_HP3ParClient_MockSSH.py
test/test_HP3ParClient_Stats.py
test/test_HP3ParClient_VLUN.py
test/test_HP3ParClient_host.py
test/test_HP3ParClient_ports.py
test/test_HP3ParClient_retry.py
test/test_HP3ParClient_system.py
test/test_HP3ParClient_volume.py