Metadata-Version: 1.1
Name: hp3parclient
Version: 3.3.2
Summary: HP 3PAR HTTP REST Client
Home-page: http://packages.python.org/hp3parclient
Author: Walter A. Boring IV
Author-email: walter.boring@hp.com
License: Apache License, Version 2.0
Keywords: hp,3par,rest
Platform: UNKNOWN
Classifier: Development Status :: 5 - Production/Stable
Classifier: Intended Audience :: Developers
Classifier: License :: OSI Approved :: Apache Software License
Classifier: Environment :: Web Environment
Classifier: Programming Language :: Python
Classifier: Programming Language :: Python :: 2.6
Classifier: Programming Language :: Python :: 2.7
Classifier: Programming Language :: Python :: 3.4
Classifier: Topic :: Internet :: WWW/HTTP
Requires: paramiko
Requires: eventlet
Requires: requests
Provides: hp3parclient
